flatblocks/__init__.py
flatblocks/admin.py
flatblocks/forms.py
flatblocks/models.py
flatblocks/settings.py
flatblocks/urls.py
flatblocks/views.py
flatblocks/locale/de/LC_MESSAGES/django.mo
flatblocks/locale/de/LC_MESSAGES/django.po
flatblocks/locale/hu/LC_MESSAGES/django.mo
flatblocks/locale/hu/LC_MESSAGES/django.po
flatblocks/locale/no/LC_MESSAGES/django.mo
flatblocks/locale/no/LC_MESSAGES/django.po
flatblocks/locale/ru/LC_MESSAGES/django.mo
flatblocks/locale/ru/LC_MESSAGES/django.po
flatblocks/management/__init__.py
flatblocks/management/commands/__init__.py
flatblocks/management/commands/createflatblock.py
flatblocks/management/commands/deleteflatblock.py
flatblocks/management/commands/unassignedflatblocks.py
flatblocks/migrations/0001_initial.py
flatblocks/migrations/__init__.py
flatblocks/south_migrations/0001_initial.py
flatblocks/south_migrations/0002_auto__chg_field_flatblock_content__chg_field_flatblock_header.py
flatblocks/south_migrations/__init__.py
flatblocks/templates/flatblocks/edit.html
flatblocks/templates/flatblocks/flatblock.html
flatblocks/templatetags/__init__.py
flatblocks/templatetags/flatblocks.py
django_flatblocks-1.0.0.dist-info/AUTHORS.txt
django_flatblocks-1.0.0.dist-info/LICENSE.txt
django_flatblocks-1.0.0.dist-info/METADATA
django_flatblocks-1.0.0.dist-info/WHEEL
django_flatblocks-1.0.0.dist-info/top_level.txt
django_flatblocks-1.0.0.dist-info/RECORD
